[
    {
        "name": "Nathan Thai",
        "title": "Co-President",
        "linkedin": "https://www.linkedin.com/in/nathanjthai/",
        "github": "https://github.com/daganaa",
        "image": "board/nathaniel_thai.jpeg"
    },
    {
        "name": "Audrey Xiao",
        "title": "Co-President",
        "linkedin": "https://www.linkedin.com/in/audrey-xiao-48231b2a7/",
        "github": "https://github.com/audreyxiao",
        "image": "board/audrey_xiao.png"
    },
    {
        "name": "Andy Bello",
        "title": "Events Team Lead",
        "linkedin": "https://www.linkedin.com/in/andy-bello/",
        "github": "https://github.com/andybello28",
        "image": "board/andy_bello.jpeg"
    },
    {
        "name": "Nate Roachford",
        "title": "Events Team",
        "linkedin": "https://www.linkedin.com/in/nate-roachford/",
        "github": "https://github.com/austinchan-orsini",
        "image": "board/nate_roachford.jpg"
    },
    {
        "name": "Jack Stanick",
        "title": "Events Team",
        "linkedin": "https://www.linkedin.com/in/jackstanick/",
        "github": "https://github.com/jackstanick04",
        "image": "board/jack_stanick.jpeg"
    },
    {
        "name": "Clare Greaney",
        "title": "Events Team",
        "linkedin": "https://www.linkedin.com/in/clare-greaney-b955ab297/",
        "github": "https://github.com/austinchan-orsini",
        "image": "board/clare_greaney.jpeg"
    },
    {
        "name": "Austin Chan-Orsini",
        "title": "Tech Team Lead",
        "linkedin": "https://www.linkedin.com/in/austinchan-orsini/",
        "github": "https://github.com/austinchan-orsini/",
        "image": "board/austin_chan-orsini.jpeg"
    },
    {
        "name": "Cameron Wright",
        "title": "Tech Team",
        "linkedin": "https://www.linkedin.com/in/cameron-wright-895aa7228/",
        "github": "https://github.com/Cameron0629",
        "image": "board/cameron_wright.png"
    },
    {
        "name": "Dylan D'Rozario",
        "title": "Tech Team",
        "linkedin": "https://www.linkedin.com/in/dylan-drozario/",
        "github": "https://github.com/dylandrozario",
        "image": "board/dylan_d'rozario.jpg"
    },
    {
        "name": "Baeram Alfreh",
        "title": "Tech Team",
        "linkedin": "https://www.linkedin.com/in/baeram-alfreh/",
        "github": "https://github.com/BaeramAl",
        "image": "board/baeram_alfreh.JPG"
    },
    {
        "name": "Catherine Hou",
        "title": "Marketing Team Lead",
        "linkedin": "https://www.linkedin.com/in/catherinehou165/",
        "github": "https://github.com/houcb",
        "image": "board/catherine_hou.jpeg"
    },
    {
        "name": "Matt Kearney",
        "title": "Marketing Team",
        "linkedin": "https://www.linkedin.com/in/matthew-kearney-053735380/",
        "github": "https://github.com/austinchan-orsini",
        "image": "board/matthew_kearney.jpg"
    },
    {
        "name": "Jackson Mendes",
        "title": "Marketing Team",
        "linkedin": "https://www.linkedin.com/in/jackson-mendes-75358634b/",
        "github": "https://github.com/austinchan-orsini",
        "image": "board/jackson_mendes.JPG"
    },
    {
        "name": "Philip Daverio",
        "title": "Treasurer",
        "linkedin": "https://www.linkedin.com/in/philip-daverio-9642aa340/",
        "github": "https://github.com/austinchan-orsini",
        "image": "board/philip_daverio.jpeg"
    }
]